[{"name":"rur","value":"NAO","domain":".instagram.com","path":"/","expires":-1,"size":6,"httpOnly":true,"secure":true,"session":true},{"name":"shbid","value":"9058","domain":".instagram.com","path":"/","expires":1619447155.510245,"size":9,"httpOnly":true,"secure":true,"session":false},{"name":"shbts","value":"1618842288.0909305","domain":".instagram.com","path":"/","expires":1619447155.510376,"size":23,"httpOnly":true,"secure":true,"session":false},{"name":"sessionid","value":"46109795646%3A2X83fIBLj9NScv%3A12","domain":".instagram.com","path":"/","expires":1650378355.009575,"size":42,"httpOnly":true,"secure":true,"session":false},{"name":"mid","value":"YH2SpgALAAEwYbe2u69USEkeFGAc","domain":".instagram.com","path":"/","expires":1681914345.758259,"size":31,"httpOnly":false,"secure":true,"session":false},{"name":"csrftoken","value":"pjuscE9ESAmq4ymZOIIUOgqadv5bzvcr","domain":".instagram.com","path":"/","expires":1650291957.54854,"size":41,"httpOnly":false,"secure":true,"session":false},{"name":"ig_nrcb","value":"1","domain":".instagram.com","path":"/","expires":1650378345.429837,"size":8,"httpOnly":false,"secure":true,"session":false},{"name":"ds_user_id","value":"46109795646","domain":".instagram.com","path":"/","expires":1626618357.548678,"size":21,"httpOnly":false,"secure":true,"session":false},{"name":"ig_did","value":"443D2A79-A400-46B5-84FF-CEF788354407","domain":".instagram.com","path":"/","expires":1681914345.42971,"size":42,"httpOnly":true,"secure":true,"session":false}]